ffvoice/__init__.py
ffvoice/Release/FLAC.dll
ffvoice/Release/_ffvoice.cp311-win_amd64.pyd
ffvoice/Release/ogg.dll
ffvoice/Release/portaudio.dll
ffvoice-0.6.0.dist-info/licenses/LICENSE
ffvoice-0.6.0.dist-info/METADATA
ffvoice-0.6.0.dist-info/WHEEL
ffvoice-0.6.0.dist-info/top_level.txt
ffvoice-0.6.0.dist-info/RECORD
