Metadata-Version: 2.4
Name: ffvoice
Version: 0.6.0
Summary: High-performance offline speech recognition library for Python
Home-page: https://github.com/chicogong/ffvoice-engine
Author: ffvoice-engine contributors
Author-email: 
License: MIT
Project-URL: Homepage, https://github.com/chicogong/ffvoice-engine
Project-URL: Bug Reports, https://github.com/chicogong/ffvoice-engine/issues
Project-URL: Source, https://github.com/chicogong/ffvoice-engine
Keywords: speech-recognition,asr,whisper,voice-activity-detection,noise-reduction,rnnoise,offline-transcription,real-time-audio
Classifier: Development Status :: 3 - Alpha
Classifier: Intended Audience :: Developers
Classifier: Intended Audience :: Science/Research
Classifier: Topic :: Multimedia :: Sound/Audio :: Speech
Classifier: Topic :: Scientific/Engineering :: Artificial Intelligence
Classifier: Programming Language :: Python :: 3
Classifier: Programming Language :: Python :: 3.9
Classifier: Programming Language :: Python :: 3.10
Classifier: Programming Language :: Python :: 3.11
Classifier: Programming Language :: Python :: 3.12
Classifier: Programming Language :: C++
Classifier: Operating System :: MacOS :: MacOS X
Classifier: Operating System :: POSIX :: Linux
Classifier: Operating System :: Microsoft :: Windows
Requires-Python: >=3.9
License-File: LICENSE
Provides-Extra: dev
Requires-Dist: pytest>=7.0; extra == "dev"
Requires-Dist: pytest-cov>=4.0; extra == "dev"
Requires-Dist: black>=23.0; extra == "dev"
Requires-Dist: flake8>=6.0; extra == "dev"
Requires-Dist: mypy>=1.0; extra == "dev"
Provides-Extra: numpy
Requires-Dist: numpy>=1.20; extra == "numpy"
Dynamic: home-page
Dynamic: license-file
Dynamic: requires-python
